[
    {
        "S&P 500 Futuros": "3.841,88",
        "data": "21/01/2021 14:48:36"
    },
    {
        "S&P 500 Futuros": "3.841,62",
        "data": "21/01/2021 14:48:42"
    },
    {
        "S&P 500 Futuros": "3.841,88",
        "data": "21/01/2021 14:48:55"
    },
    {
        "S&P 500 Futuros": "3.841,62",
        "data": "21/01/2021 14:48:57"
    },
    {
        "S&P 500 Futuros": "3.841,88",
        "data": "21/01/2021 14:48:59"
    },
    {
        "S&P 500 Futuros": "3.841,62",
        "data": "21/01/2021 14:49:06"
    },
    {
        "S&P 500 Futuros": "3.841,88",
        "data": "21/01/2021 14:49:18"
    },
    {
        "S&P 500 Futuros": "3.841,62",
        "data": "21/01/2021 14:49:25"
    },
    {
        "S&P 500 Futuros": "3.841,38",
        "data": "21/01/2021 14:50:16"
    },
    {
        "S&P 500 Futuros": "3.840,88",
        "data": "21/01/2021 14:50:28"
    },
    {
        "S&P 500 Futuros": "3.840,62",
        "data": "21/01/2021 14:50:39"
    },
    {
        "S&P 500 Futuros": "3.840,38",
        "data": "21/01/2021 14:50:47"
    },
    {
        "S&P 500 Futuros": "3.840,12",
        "data": "21/01/2021 14:50:49"
    },
    {
        "S&P 500 Futuros": "3.840,38",
        "data": "21/01/2021 14:50:56"
    },
    {
        "S&P 500 Futuros": "3.840,62",
        "data": "21/01/2021 14:51:09"
    },
    {
        "S&P 500 Futuros": "3.840,12",
        "data": "21/01/2021 14:51:20"
    },
    {
        "S&P 500 Futuros": "3.839,88",
        "data": "21/01/2021 14:51:25"
    },
    {
        "S&P 500 Futuros": "3.839,75",
        "data": "21/01/2021 14:51:38"
    },
    {
        "S&P 500 Futuros": "3.839,38",
        "data": "21/01/2021 14:51:40"
    },
    {
        "S&P 500 Futuros": "3.839,75",
        "data": "21/01/2021 14:51:42"
    },
    {
        "S&P 500 Futuros": "3.839,38",
        "data": "21/01/2021 14:51:45"
    },
    {
        "S&P 500 Futuros": "3.839,62",
        "data": "21/01/2021 14:51:49"
    },
    {
        "S&P 500 Futuros": "3.839,12",
        "data": "21/01/2021 14:52:18"
    },
    {
        "S&P 500 Futuros": "3.839,38",
        "data": "21/01/2021 14:52:37"
    }
]