[
    {
        "S&P 500 Futuros": "3.818,38",
        "data": "20/01/2021 11:58:48"
    },
    {
        "S&P 500 Futuros": "3.818,62",
        "data": "20/01/2021 11:58:52"
    },
    {
        "S&P 500 Futuros": "3.818,38",
        "data": "20/01/2021 11:58:58"
    },
    {
        "S&P 500 Futuros": "3.818,62",
        "data": "20/01/2021 11:59:02"
    },
    {
        "S&P 500 Futuros": "3.818,12",
        "data": "20/01/2021 11:59:05"
    },
    {
        "S&P 500 Futuros": "3.818,25",
        "data": "20/01/2021 11:59:07"
    },
    {
        "S&P 500 Futuros": "3.818,12",
        "data": "20/01/2021 11:59:09"
    },
    {
        "S&P 500 Futuros": "3.818,25",
        "data": "20/01/2021 11:59:11"
    },
    {
        "S&P 500 Futuros": "3.818,62",
        "data": "20/01/2021 11:59:12"
    },
    {
        "S&P 500 Futuros": "3.818,25",
        "data": "20/01/2021 11:59:14"
    },
    {
        "S&P 500 Futuros": "3.818,62",
        "data": "20/01/2021 11:59:16"
    },
    {
        "S&P 500 Futuros": "3.818,12",
        "data": "20/01/2021 11:59:19"
    },
    {
        "S&P 500 Futuros": "3.817,88",
        "data": "20/01/2021 11:59:22"
    },
    {
        "S&P 500 Futuros": "3.818,38",
        "data": "20/01/2021 11:59:26"
    },
    {
        "S&P 500 Futuros": "3.818,12",
        "data": "20/01/2021 11:59:52"
    },
    {
        "S&P 500 Futuros": "3.819,12",
        "data": "20/01/2021 12:00:11"
    },
    {
        "S&P 500 Futuros": "3.818,25",
        "data": "20/01/2021 12:00:14"
    },
    {
        "S&P 500 Futuros": "3.818,88",
        "data": "20/01/2021 12:00:22"
    },
    {
        "S&P 500 Futuros": "3.819,12",
        "data": "20/01/2021 12:00:29"
    },
    {
        "S&P 500 Futuros": "3.819,88",
        "data": "20/01/2021 12:00:42"
    },
    {
        "S&P 500 Futuros": "3.819,62",
        "data": "20/01/2021 12:00:47"
    },
    {
        "S&P 500 Futuros": "3.819,88",
        "data": "20/01/2021 12:00:52"
    },
    {
        "S&P 500 Futuros": "3.819,62",
        "data": "20/01/2021 12:00:54"
    },
    {
        "S&P 500 Futuros": "3.819,88",
        "data": "20/01/2021 12:00:55"
    },
    {
        "S&P 500 Futuros": "3.819,62",
        "data": "20/01/2021 12:01:00"
    },
    {
        "S&P 500 Futuros": "3.819,38",
        "data": "20/01/2021 12:01:02"
    },
    {
        "S&P 500 Futuros": "3.819,12",
        "data": "20/01/2021 12:01:05"
    },
    {
        "S&P 500 Futuros": "3.819,38",
        "data": "20/01/2021 12:01:21"
    },
    {
        "S&P 500 Futuros": "3.819,62",
        "data": "20/01/2021 12:01:32"
    },
    {
        "S&P 500 Futuros": "3.820,12",
        "data": "20/01/2021 12:01:34"
    },
    {
        "S&P 500 Futuros": "3.819,62",
        "data": "20/01/2021 12:01:36"
    },
    {
        "S&P 500 Futuros": "3.820,12",
        "data": "20/01/2021 12:01:44"
    },
    {
        "S&P 500 Futuros": "3.819,38",
        "data": "20/01/2021 12:01:53"
    },
    {
        "S&P 500 Futuros": "3.820,12",
        "data": "20/01/2021 12:02:16"
    },
    {
        "S&P 500 Futuros": "3.820,62",
        "data": "20/01/2021 12:02:26"
    }
]